dsnd_probability/Binomialdistribution.py
dsnd_probability/Gaussiandistribution.py
dsnd_probability/Generaldistribution.py
dsnd_probability/__init__.py
example_probability/Binomialdistribution.py
example_probability/Gaussiandistribution.py
example_probability/Generaldistribution.py
example_probability/__init__.py
example_probability-1.5.dist-info/METADATA
example_probability-1.5.dist-info/WHEEL
example_probability-1.5.dist-info/top_level.txt
example_probability-1.5.dist-info/RECORD
