Metadata-Version: 2.1
Name: example-probability
Version: 1.5
Summary: Gaussian and Binomial distributions
Home-page: UNKNOWN
Author: Andrew Paster
Author-email: myemail@something.com
License: UNKNOWN
Platform: UNKNOWN
